{
  "title": "IFMSA Policy Proposal Mental Health for All",
  "outline": [
    {
      "level": "H1",
      "text": "IFMSA Policy Proposal Mental Health for All",
      "page": 1,
      "children": [
        {
          "level": "H3",
          "text": "Proposed by Team of Officials",
          "page": 1,
          "children": []
        },
        {
          "level": "H3",
          "text": "Presented to the IFMSA General Assembly March Meeting 2025.",
          "page": 1,
          "children": []
        },
        {
          "level": "H3",
          "text": "Policy Commission",
          "page": 1,
          "children": []
        },
        {
          "level": "H3",
          "text": "24/25,  lra@ifmsa.org",
          "page": 1,
          "children": []
        },
        {
          "level": "H3",
          "text": "Policy Contributors:",
          "page": 1,
          "children": []
        },
        {
          "level": "H3",
          "text": "Policy Statement",
          "page": 2,
          "children": []
        },
        {
          "level": "H3",
          "text": "IFMSA position",
          "page": 2,
          "children": []
        },
        {
          "level": "H3",
          "text": "Call to Action",
          "page": 2,
          "children": []
        },
        {
          "level": "H3",
          "text": "Governments and Health Ministries  to:",
          "page": 2,
          "children": []
        },
        {
          "level": "H3",
          "text": "Healthcare Institutions and Providers  to:",
          "page": 2,
          "children": []
        },
        {
          "level": "H3",
          "text": "Medical Universities, Faculties, and Research Institutions  to:",
          "page": 3,
          "children": []
        },
        {
          "level": "H3",
          "text": "The Private Sector  to:",
          "page": 3,
          "children": []
        },
        {
          "level": "H3",
          "text": "IFMSA National Member Organisations (NMOs) and Healthcare Students Worldwide  to:",
          "page": 3,
          "children": []
        },
        {
          "level": "H3",
          "text": "Position Paper",
          "page": 4,
          "children": []
        },
        {
          "level": "H3",
          "text": "Background information",
          "page": 4,
          "children": []
        },
        {
          "level": "H3",
          "text": "1. Mental Health as a Component of Health and Well-Being",
          "page": 4,
          "children": []
        },
        {
          "level": "H3",
          "text": "1.1 The Bidirectional Link between Physical and Mental Health",
          "page": 4,
          "children": []
        },
        {
          "level": "H3",
          "text": "1.2 Mental Health and Non-Communicable Diseases",
          "page": 5,
          "children": []
        },
        {
          "level": "H3",
          "text": "1.3 The Global Burden of Mental Health Challenges",
          "page": 5,
          "children": []
        },
        {
          "level": "H3",
          "text": "healthcare, and efforts to reduce stigma and discrimination (2).",
          "page": 5,
          "children": []
        },
        {
          "level": "H3",
          "text": "1.4 Regional Mental Health: Disparities and Inequities",
          "page": 5,
          "children": []
        },
        {
          "level": "H3",
          "text": "1.5 Mental Health in Medical Students and the Health Workforce",
          "page": 6,
          "children": []
        },
        {
          "level": "H3",
          "text": "2. Mental Health Across the Lifecourse",
          "page": 6,
          "children": []
        },
        {
          "level": "H3",
          "text": "2.1 Children, Adolescents, and Young Adults",
          "page": 6,
          "children": []
        },
        {
          "level": "H3",
          "text": "2.2 Maternal and Perinatal Mental Health",
          "page": 6,
          "children": []
        },
        {
          "level": "H3",
          "text": "2.3 Older Adults",
          "page": 6,
          "children": []
        },
        {
          "level": "H3",
          "text": "3. Access to Mental Health Care",
          "page": 7,
          "children": []
        },
        {
          "level": "H3",
          "text": "3.1 Mental Health and Human Rights",
          "page": 7,
          "children": []
        },
        {
          "level": "H3",
          "text": "3.2 Financial and Physical Resources",
          "page": 7,
          "children": []
        },
        {
          "level": "H3",
          "text": "3.3 Legislation and Policy",
          "page": 8,
          "children": []
        },
        {
          "level": "H3",
          "text": "3.4 Innovative Models of Care - Including Technology",
          "page": 8,
          "children": []
        },
        {
          "level": "H3",
          "text": "4. Barriers to Mental Health Care",
          "page": 9,
          "children": []
        },
        {
          "level": "H3",
          "text": "4.1 Chronic Conditions and Comorbidities",
          "page": 9,
          "children": []
        },
        {
          "level": "H3",
          "text": "4.2 Vulnerable Populations 4.2.1 People with disabilities",
          "page": 10,
          "children": []
        },
        {
          "level": "H3",
          "text": "4.2.2 People Experiencing Poverty",
          "page": 10,
          "children": []
        },
        {
          "level": "H3",
          "text": "4.2.3 LGBTQIA+ Individuals",
          "page": 10,
          "children": []
        },
        {
          "level": "H3",
          "text": "4.2.4 Black, Indigenous, and People of Colour (BIPOC)",
          "page": 10,
          "children": []
        },
        {
          "level": "H3",
          "text": "4.2.5 Migrants",
          "page": 11,
          "children": []
        },
        {
          "level": "H3",
          "text": "4.2.6 Displaced Persons and Refugees",
          "page": 11,
          "children": []
        },
        {
          "level": "H3",
          "text": "4.3 Multiple and Overlapping Vulnerabilities",
          "page": 12,
          "children": []
        },
        {
          "level": "H3",
          "text": "5. Social and Cultural Dimensions of Mental Health",
          "page": 12,
          "children": []
        },
        {
          "level": "H3",
          "text": "5.1 Stigmatisation and Individual and Societal Effects",
          "page": 12,
          "children": []
        },
        {
          "level": "H3",
          "text": "5.2 Media and Reporting on Mental Health",
          "page": 13,
          "children": []
        },
        {
          "level": "H3",
          "text": "5.3 Effects of Social Media",
          "page": 14,
          "children": []
        },
        {
          "level": "H3",
          "text": "5.4 Social Isolation",
          "page": 14,
          "children": []
        },
        {
          "level": "H3",
          "text": "6. Mental Health in Global Challenges",
          "page": 14,
          "children": []
        },
        {
          "level": "H3",
          "text": "6.1 Mental Health in Health Emergencies",
          "page": 15,
          "children": []
        },
        {
          "level": "H3",
          "text": "6.2 Conflict, Humanitarian Crises, and Mental Health",
          "page": 15,
          "children": []
        },
        {
          "level": "H3",
          "text": "6.3 The Climate Crisis and Mental Health",
          "page": 15,
          "children": []
        },
        {
          "level": "H3",
          "text": "7. Research and Data on Mental Health",
          "page": 16,
          "children": []
        },
        {
          "level": "H3",
          "text": "7.1 Regional Inequities in Research and Data",
          "page": 16,
          "children": []
        },
        {
          "level": "H3",
          "text": "7.2 Involvement of People with Lived Experience",
          "page": 17,
          "children": []
        },
        {
          "level": "H3",
          "text": "8. Mental Health Literacy (MHL)",
          "page": 18,
          "children": []
        },
        {
          "level": "H3",
          "text": "8.1 Empowering Communities Through Knowledge",
          "page": 18,
          "children": []
        },
        {
          "level": "H3",
          "text": "8.2 Mental-Health-Informed Training in Medical Education",
          "page": 18,
          "children": []
        },
        {
          "level": "H3",
          "text": "8.3 Role of Health Professionals in Promoting MHL",
          "page": 19,
          "children": []
        },
        {
          "level": "H3",
          "text": "9. Mental Health in All Policies",
          "page": 19,
          "children": []
        },
        {
          "level": "H3",
          "text": "10. IFMSA Contributions",
          "page": 20,
          "children": []
        }
      ]
    }
  ]
}